pymongo_orm/__init__.py
pymongo_orm/abstract/__init__.py
pymongo_orm/abstract/connection.py
pymongo_orm/abstract/implementation.py
pymongo_orm/abstract/model.py
pymongo_orm/async_model/__init__.py
pymongo_orm/async_model/connection.py
pymongo_orm/async_model/implementation.py
pymongo_orm/async_model/model.py
pymongo_orm/config.py
pymongo_orm/exceptions.py
pymongo_orm/sync_model/__init__.py
pymongo_orm/sync_model/connection.py
pymongo_orm/sync_model/implementation.py
pymongo_orm/sync_model/model.py
pymongo_orm/utils/converters.py
pymongo_orm/utils/decorators.py
pymongo_orm/utils/logging.py
pymongo_orm-0.1.3.dist-info/LICENSE
pymongo_orm-0.1.3.dist-info/METADATA
pymongo_orm-0.1.3.dist-info/WHEEL
pymongo_orm-0.1.3.dist-info/RECORD
