Metadata-Version: 2.3
Name: pymongo-orm
Version: 0.1.3
Summary: A lightweight, flexible Object-Relational Mapping (ORM) for MongoDB in Python
License: MIT
Keywords: mongodb,orm,database,pymongo,motor,async,pydantic
Author: Oluwaleye Victor
Author-email: o.oluwaleye93@gmail.com
Requires-Python: >=3.9,<4.0
Classifier: Development Status :: 4 - Beta
Classifier: Intended Audience :: Developers
Classifier: License :: OSI Approved :: MIT License
Classifier: Programming Language :: Python :: 3
Classifier: Programming Language :: Python :: 3.9
Classifier: Programming Language :: Python :: 3.10
Classifier: Programming Language :: Python :: 3.11
Classifier: Programming Language :: Python :: 3.12
Classifier: Programming Language :: Python :: 3.13
Classifier: Topic :: Database
Classifier: Topic :: Software Development :: Libraries
Classifier: Topic :: Software Development :: Libraries :: Python Modules
Classifier: Typing :: Typed
Requires-Dist: motor (>=3.7.0,<4.0.0)
Requires-Dist: pydantic (>=2.11.3,<3.0.0)
Project-URL: Documentation, https://drlsv91.github.io/pymongo_orm/
Project-URL: Homepage, https://github.com/drlsv91/pymongo_orm
Project-URL: Repository, https://github.com/drlsv91/pymongo_orm
